[
    {
        "id": "07d74addcefdab2b",
        "type": "tab",
        "label": "Flow 1",
        "disabled": false,
        "info": "",
        "env": []
    },
    {
        "id": "3ce6d72ecdcefa9b",
        "type": "tab",
        "label": "Flow 2",
        "disabled": false,
        "info": "",
        "env": []
    },
    {
        "id": "ebaade6de9106c36",
        "type": "inject",
        "z": "07d74addcefdab2b",
        "name": "",
        "props": [
            {
                "p": "payload"
            },
            {
                "p": "topic",
                "vt": "str"
            }
        ],
        "repeat": "",
        "crontab": "",
        "once": false,
        "onceDelay": 0.1,
        "topic": "",
        "payload": "",
        "payloadType": "date",
        "x": 100,
        "y": 120,
        "wires": [
            [
                "f3076698ece5b88a"
            ]
        ]
    },
    {
        "id": "f3076698ece5b88a",
        "type": "function",
        "z": "07d74addcefdab2b",
        "name": "",
        "func": "let count = context.get(\"count\") || 0;\ncount += 1;\n\ncontext.set('count', count);\nflow.set('temp', count);\n\nmsg.count = count;\nreturn msg;",
        "outputs": 1,
        "noerr": 0,
        "initialize": "",
        "finalize": "",
        "libs": [],
        "x": 280,
        "y": 120,
        "wires": [
            [
                "e2c7b7a67d20f15d"
            ]
        ]
    },
    {
        "id": "e2c7b7a67d20f15d",
        "type": "debug",
        "z": "07d74addcefdab2b",
        "name": "",
        "active": true,
        "tosidebar": true,
        "console": false,
        "tostatus": false,
        "complete": "true",
        "targetType": "full",
        "statusVal": "",
        "statusType": "auto",
        "x": 470,
        "y": 120,
        "wires": []
    },
    {
        "id": "0a735e5cce88086e",
        "type": "inject",
        "z": "07d74addcefdab2b",
        "name": "get flow temp",
        "props": [
            {
                "p": "payload"
            },
            {
                "p": "topic",
                "vt": "str"
            }
        ],
        "repeat": "",
        "crontab": "",
        "once": false,
        "onceDelay": 0.1,
        "topic": "",
        "payload": "temp",
        "payloadType": "flow",
        "x": 110,
        "y": 40,
        "wires": [
            [
                "e2c7b7a67d20f15d"
            ]
        ]
    },
    {
        "id": "e85ab3b7a990d709",
        "type": "function",
        "z": "07d74addcefdab2b",
        "name": "increment flow count",
        "func": "const count = msg.payload;\nmsg.payload = count + 1;\nreturn msg;",
        "outputs": 1,
        "noerr": 0,
        "initialize": "",
        "finalize": "",
        "libs": [],
        "x": 500,
        "y": 220,
        "wires": [
            [
                "d85759c5f4c22247"
            ]
        ]
    },
    {
        "id": "d85759c5f4c22247",
        "type": "switch",
        "z": "07d74addcefdab2b",
        "name": "loop condition",
        "property": "payload",
        "propertyType": "msg",
        "rules": [
            {
                "t": "lt",
                "v": "count",
                "vt": "flow"
            },
            {
                "t": "gte",
                "v": "count",
                "vt": "flow"
            }
        ],
        "checkall": "true",
        "repair": true,
        "outputs": 2,
        "x": 500,
        "y": 300,
        "wires": [
            [
                "e85ab3b7a990d709",
                "dda844b6cbd4e907"
            ],
            [
                "dda844b6cbd4e907"
            ]
        ]
    },
    {
        "id": "c933c00cec83d260",
        "type": "change",
        "z": "07d74addcefdab2b",
        "name": "",
        "rules": [
            {
                "t": "set",
                "p": "payload",
                "pt": "msg",
                "to": "1",
                "tot": "num"
            },
            {
                "t": "set",
                "p": "count",
                "pt": "flow",
                "to": "temp",
                "tot": "flow"
            }
        ],
        "action": "",
        "property": "",
        "from": "",
        "to": "",
        "reg": false,
        "x": 280,
        "y": 300,
        "wires": [
            [
                "d85759c5f4c22247"
            ]
        ]
    },
    {
        "id": "09698c4fa4dfc453",
        "type": "inject",
        "z": "07d74addcefdab2b",
        "name": "",
        "props": [
            {
                "p": "payload"
            },
            {
                "p": "topic",
                "vt": "str"
            }
        ],
        "repeat": "",
        "crontab": "",
        "once": false,
        "onceDelay": 0.1,
        "topic": "",
        "payload": "",
        "payloadType": "date",
        "x": 100,
        "y": 300,
        "wires": [
            [
                "c933c00cec83d260"
            ]
        ]
    },
    {
        "id": "a39a10c03b021eb5",
        "type": "debug",
        "z": "07d74addcefdab2b",
        "name": "",
        "active": true,
        "tosidebar": true,
        "console": false,
        "tostatus": false,
        "complete": "false",
        "statusVal": "",
        "statusType": "auto",
        "x": 870,
        "y": 300,
        "wires": []
    },
    {
        "id": "dda844b6cbd4e907",
        "type": "template",
        "z": "07d74addcefdab2b",
        "name": "",
        "field": "payload",
        "fieldType": "msg",
        "format": "handlebars",
        "syntax": "mustache",
        "template": "Count: {{payload}} ",
        "output": "str",
        "x": 700,
        "y": 300,
        "wires": [
            [
                "a39a10c03b021eb5"
            ]
        ]
    },
    {
        "id": "27028113e111c0f0",
        "type": "inject",
        "z": "07d74addcefdab2b",
        "name": "",
        "props": [
            {
                "p": "payload"
            },
            {
                "p": "topic",
                "vt": "str"
            }
        ],
        "repeat": "",
        "crontab": "",
        "once": false,
        "onceDelay": 0.1,
        "topic": "",
        "payload": "1",
        "payloadType": "num",
        "x": 90,
        "y": 460,
        "wires": [
            [
                "76fb0ee15d01eaf8"
            ]
        ]
    },
    {
        "id": "16ddc8c7ac87d6b6",
        "type": "link out",
        "z": "07d74addcefdab2b",
        "name": "",
        "mode": "link",
        "links": [
            "0b7f4df66c6fac66",
            "3489b424932762e8"
        ],
        "x": 405,
        "y": 500,
        "wires": []
    },
    {
        "id": "76fb0ee15d01eaf8",
        "type": "function",
        "z": "07d74addcefdab2b",
        "name": "isPositive",
        "func": "const num = msg.payload;\nif ( num > 0 ) {\n    return msg\n}\nthrow 'Negative number!'",
        "outputs": 1,
        "noerr": 0,
        "initialize": "",
        "finalize": "",
        "libs": [],
        "x": 260,
        "y": 500,
        "wires": [
            [
                "16ddc8c7ac87d6b6"
            ]
        ]
    },
    {
        "id": "1f14aad202527486",
        "type": "inject",
        "z": "07d74addcefdab2b",
        "name": "",
        "props": [
            {
                "p": "payload"
            },
            {
                "p": "topic",
                "vt": "str"
            }
        ],
        "repeat": "",
        "crontab": "",
        "once": false,
        "onceDelay": 0.1,
        "topic": "",
        "payload": "-1",
        "payloadType": "num",
        "x": 90,
        "y": 540,
        "wires": [
            [
                "76fb0ee15d01eaf8"
            ]
        ]
    },
    {
        "id": "c27f94d2ff9b0625",
        "type": "catch",
        "z": "07d74addcefdab2b",
        "name": "",
        "scope": [
            "76fb0ee15d01eaf8"
        ],
        "uncaught": false,
        "x": 250,
        "y": 580,
        "wires": [
            [
                "e9337c32d7c65c2e"
            ]
        ]
    },
    {
        "id": "310d994857a2b82a",
        "type": "status",
        "z": "07d74addcefdab2b",
        "name": "",
        "scope": [
            "76fb0ee15d01eaf8"
        ],
        "x": 260,
        "y": 640,
        "wires": [
            [
                "c4d964fbc2d82353"
            ]
        ]
    },
    {
        "id": "24ef1717c0f368d0",
        "type": "debug",
        "z": "07d74addcefdab2b",
        "name": "",
        "active": true,
        "tosidebar": true,
        "console": false,
        "tostatus": false,
        "complete": "true",
        "targetType": "full",
        "statusVal": "",
        "statusType": "auto",
        "x": 570,
        "y": 580,
        "wires": []
    },
    {
        "id": "397ceceeb920b99b",
        "type": "debug",
        "z": "07d74addcefdab2b",
        "name": "",
        "active": true,
        "tosidebar": true,
        "console": false,
        "tostatus": false,
        "complete": "true",
        "targetType": "full",
        "statusVal": "",
        "statusType": "auto",
        "x": 570,
        "y": 640,
        "wires": []
    },
    {
        "id": "e9337c32d7c65c2e",
        "type": "delay",
        "z": "07d74addcefdab2b",
        "name": "",
        "pauseType": "delay",
        "timeout": "3",
        "timeoutUnits": "seconds",
        "rate": "1",
        "nbRateUnits": "1",
        "rateUnits": "second",
        "randomFirst": "1",
        "randomLast": "5",
        "randomUnits": "seconds",
        "drop": false,
        "allowrate": false,
        "outputs": 1,
        "x": 440,
        "y": 580,
        "wires": [
            [
                "24ef1717c0f368d0"
            ]
        ]
    },
    {
        "id": "c4d964fbc2d82353",
        "type": "delay",
        "z": "07d74addcefdab2b",
        "name": "",
        "pauseType": "delay",
        "timeout": "5",
        "timeoutUnits": "seconds",
        "rate": "1",
        "nbRateUnits": "1",
        "rateUnits": "second",
        "randomFirst": "1",
        "randomLast": "5",
        "randomUnits": "seconds",
        "drop": false,
        "allowrate": false,
        "outputs": 1,
        "x": 440,
        "y": 640,
        "wires": [
            [
                "397ceceeb920b99b"
            ]
        ]
    },
    {
        "id": "e2649496bd8d295c",
        "type": "e-mail",
        "z": "07d74addcefdab2b",
        "server": "smtp.gmail.com",
        "port": "465",
        "secure": true,
        "tls": true,
        "name": "",
        "dname": "",
        "x": 530,
        "y": 860,
        "wires": []
    },
    {
        "id": "15f06ac740f9f2c3",
        "type": "inject",
        "z": "07d74addcefdab2b",
        "name": "",
        "props": [
            {
                "p": "payload"
            },
            {
                "p": "topic",
                "vt": "str"
            }
        ],
        "repeat": "5",
        "crontab": "",
        "once": false,
        "onceDelay": 0.1,
        "topic": "",
        "payload": "",
        "payloadType": "date",
        "x": 110,
        "y": 720,
        "wires": [
            [
                "06bad34064898fba"
            ]
        ]
    },
    {
        "id": "06bad34064898fba",
        "type": "function",
        "z": "07d74addcefdab2b",
        "name": "",
        "func": "const date = new Date();\nmsg.day = date.getDay();\nreturn msg;",
        "outputs": 1,
        "noerr": 0,
        "initialize": "",
        "finalize": "",
        "libs": [],
        "x": 300,
        "y": 720,
        "wires": [
            [
                "65b7af3b7747008b"
            ]
        ]
    },
    {
        "id": "855751471fb8f83b",
        "type": "debug",
        "z": "07d74addcefdab2b",
        "name": "",
        "active": true,
        "tosidebar": true,
        "console": false,
        "tostatus": false,
        "complete": "day",
        "targetType": "msg",
        "statusVal": "",
        "statusType": "auto",
        "x": 800,
        "y": 680,
        "wires": []
    },
    {
        "id": "65b7af3b7747008b",
        "type": "rbe",
        "z": "07d74addcefdab2b",
        "name": "",
        "func": "rbe",
        "gap": "",
        "start": "",
        "inout": "out",
        "septopics": true,
        "property": "day",
        "topi": "topic",
        "x": 490,
        "y": 720,
        "wires": [
            [
                "8594902ff1a64869"
            ]
        ]
    },
    {
        "id": "8594902ff1a64869",
        "type": "switch",
        "z": "07d74addcefdab2b",
        "name": "",
        "property": "true",
        "propertyType": "jsonata",
        "rules": [
            {
                "t": "eq",
                "v": "day % 2 === 0",
                "vt": "jsonata"
            },
            {
                "t": "eq",
                "v": "day % 2 === 1",
                "vt": "jsonata"
            }
        ],
        "checkall": "true",
        "repair": false,
        "outputs": 2,
        "x": 650,
        "y": 720,
        "wires": [
            [
                "855751471fb8f83b"
            ],
            [
                "e2269043202f4b7b"
            ]
        ]
    },
    {
        "id": "e2269043202f4b7b",
        "type": "debug",
        "z": "07d74addcefdab2b",
        "name": "",
        "active": true,
        "tosidebar": true,
        "console": false,
        "tostatus": false,
        "complete": "true",
        "targetType": "full",
        "statusVal": "",
        "statusType": "auto",
        "x": 790,
        "y": 760,
        "wires": []
    },
    {
        "id": "3489b424932762e8",
        "type": "link in",
        "z": "3ce6d72ecdcefa9b",
        "name": "",
        "links": [
            "16ddc8c7ac87d6b6"
        ],
        "x": 175,
        "y": 180,
        "wires": [
            [
                "cff013d04d82d13b"
            ]
        ]
    },
    {
        "id": "cff013d04d82d13b",
        "type": "debug",
        "z": "3ce6d72ecdcefa9b",
        "name": "",
        "active": true,
        "tosidebar": true,
        "console": false,
        "tostatus": false,
        "complete": "false",
        "statusVal": "",
        "statusType": "auto",
        "x": 400,
        "y": 180,
        "wires": []
    }
]